multi_classifier_tester/__init__.py
multi_classifier_tester/classifier_tester.py
multi_classifier_tester-1.0.0.dist-info/licenses/LICENSE
multi_classifier_tester-1.0.0.dist-info/METADATA
multi_classifier_tester-1.0.0.dist-info/WHEEL
multi_classifier_tester-1.0.0.dist-info/top_level.txt
multi_classifier_tester-1.0.0.dist-info/RECORD
